tcrfoundation/__init__.py
tcrfoundation/__version__.py
tcrfoundation/pretrain.py
tcrfoundation/.ipynb_checkpoints/pretrain-checkpoint.py
tcrfoundation/.ipynb_checkpoints/version-checkpoint.py
tcrfoundation/finetune/__init__.py
tcrfoundation/finetune/avidity.py
tcrfoundation/finetune/classification.py
tcrfoundation/finetune/cross_modal.py
tcrfoundation/finetune/specificity.py
tcrfoundation/finetune/utils.py
tcrfoundation/finetune/.ipynb_checkpoints/__init__-checkpoint.py
tcrfoundation/finetune/.ipynb_checkpoints/avidity-checkpoint.py
tcrfoundation/finetune/.ipynb_checkpoints/classification-checkpoint.py
tcrfoundation/finetune/.ipynb_checkpoints/cross_modal-checkpoint.py
tcrfoundation/finetune/.ipynb_checkpoints/specificity-checkpoint.py
tcrfoundation/finetune/.ipynb_checkpoints/utils-checkpoint.py
tcrfoundation-0.1.3.dist-info/licenses/LICENSE
tcrfoundation-0.1.3.dist-info/METADATA
tcrfoundation-0.1.3.dist-info/WHEEL
tcrfoundation-0.1.3.dist-info/top_level.txt
tcrfoundation-0.1.3.dist-info/RECORD
