Metadata-Version: 2.4
Name: tcrfoundation
Version: 0.1.3
Summary: A multimodal foundation model for T cell receptor and transcriptome analysis
Author-email: Xu Liao <xl3514@cumc.columbia.edu>
License: MIT
Project-URL: Homepage, https://github.com/Liao-Xu/TCRfoundation
Project-URL: Documentation, https://tcrfoundation.readthedocs.io
Project-URL: Repository, https://github.com/Liao-Xu/TCRfoundation
Project-URL: Issues, https://github.com/Liao-Xu/TCRfoundation/issues
Classifier: Development Status :: 3 - Alpha
Classifier: Intended Audience :: Science/Research
Classifier: Topic :: Scientific/Engineering :: Bio-Informatics
Classifier: License :: OSI Approved :: MIT License
Classifier: Programming Language :: Python :: 3
Classifier: Programming Language :: Python :: 3.8
Classifier: Programming Language :: Python :: 3.9
Classifier: Programming Language :: Python :: 3.10
Requires-Python: >=3.8
License-File: LICENSE
Requires-Dist: torch>=1.10.0
Requires-Dist: numpy>=1.20.0
Requires-Dist: pandas>=1.3.0
Requires-Dist: scanpy>=1.9.0
Requires-Dist: scikit-learn>=1.0.0
Requires-Dist: matplotlib>=3.5.0
Requires-Dist: seaborn>=0.11.0
Requires-Dist: tqdm>=4.62.0
Requires-Dist: anndata>=0.8.0
Provides-Extra: dev
Requires-Dist: pytest>=6.2.0; extra == "dev"
Requires-Dist: jupyter>=1.0.0; extra == "dev"
Requires-Dist: black>=21.0; extra == "dev"
Provides-Extra: docs
Requires-Dist: sphinx>=4.0.0; extra == "docs"
Requires-Dist: furo; extra == "docs"
Requires-Dist: myst-parser>=0.18.0; extra == "docs"
Requires-Dist: myst-nb>=0.17.0; extra == "docs"
Requires-Dist: sphinx-autodoc-typehints; extra == "docs"
Requires-Dist: sphinx-copybutton; extra == "docs"
Requires-Dist: ipykernel; extra == "docs"
Requires-Dist: nbformat; extra == "docs"
Dynamic: license-file
